envoy/dependency/check/__init__.py
envoy/dependency/check/checker.py
envoy/dependency/check/cmd.py
envoy/dependency/check/exceptions.py
envoy/dependency/check/py.typed
envoy/dependency/check/typing.py
envoy/dependency/check/abstract/__init__.py
envoy/dependency/check/abstract/checker.py
envoy/dependency/check/abstract/dependency.py
envoy/dependency/check/abstract/issues.py
envoy/dependency/check/abstract/release.py
envoy/dependency/check/abstract/cves/__init__.py
envoy/dependency/check/abstract/cves/cve.py
envoy/dependency/check/abstract/cves/cves.py
envoy.dependency.check-0.1.13.dist-info/METADATA
envoy.dependency.check-0.1.13.dist-info/WHEEL
envoy.dependency.check-0.1.13.dist-info/entry_points.txt
envoy.dependency.check-0.1.13.dist-info/namespace_packages.txt
envoy.dependency.check-0.1.13.dist-info/top_level.txt
envoy.dependency.check-0.1.13.dist-info/RECORD
