Metadata-Version: 2.1
Name: envoy.dependency.check
Version: 0.1.13
Summary: "Dependency checker used in Envoy proxy's CI"
Home-page: https://github.com/envoyproxy/toolshed/tree/main/envoy.dependency.check
Author: Ryan Northey
Author-email: ryan@synca.io
Maintainer: Ryan Northey
Maintainer-email: ryan@synca.io
License: Apache Software License 2.0
Requires-Python: >=3.10.0
Requires-Dist: abstracts (>=0.0.12)
Requires-Dist: aio.api.github (>=0.2.6)
Requires-Dist: aio.api.nist (>=0.0.4)
Requires-Dist: aio.core (>=0.10.1)
Requires-Dist: aio.run.checker (>=0.5.7)
Requires-Dist: aiohttp (>=3.8.1)
Requires-Dist: envoy.base.utils (>=0.4.7)
Requires-Dist: gidgethub
Requires-Dist: jinja2 (>=3.1.4)
Requires-Dist: packaging (>=23.0)
